codeowners/__init__.py
codeowners/py.typed
codeowners/test_codeowners.py
codeowners-0.7.0.dist-info/LICENSE
codeowners-0.7.0.dist-info/METADATA
codeowners-0.7.0.dist-info/WHEEL
codeowners-0.7.0.dist-info/RECORD
