Metadata-Version: 2.1
Name: codeowners
Version: 0.7.0
Summary: Codeowners parser for Python
Home-page: https://github.com/sbdchd/codeowners
License: MIT
Keywords: codeowners,git,github
Author: Steve Dignam
Author-email: steve@dignam.xyz
Requires-Python: >=3.7,<4.0
Classifier: License :: OSI Approved :: MIT License
Classifier: Programming Language :: Python :: 3
Classifier: Programming Language :: Python :: 3.7
Classifier: Programming Language :: Python :: 3.8
Classifier: Programming Language :: Python :: 3.9
Classifier: Programming Language :: Python :: 3.10
Classifier: Programming Language :: Python :: 3.11
Classifier: Programming Language :: Python :: 3.12
Requires-Dist: typing_extensions (>=3.7)
Project-URL: Repository, https://github.com/sbdchd/codeowners
